README.md
setup.cfg
setup.py
dsnd_g_v1_probability/Binomialdistribution.py
dsnd_g_v1_probability/Gaussiandistribution.py
dsnd_g_v1_probability/Generaldistribution.py
dsnd_g_v1_probability/__init__.py
dsnd_g_v1_probability.egg-info/PKG-INFO
dsnd_g_v1_probability.egg-info/SOURCES.txt
dsnd_g_v1_probability.egg-info/dependency_links.txt
dsnd_g_v1_probability.egg-info/not-zip-safe
dsnd_g_v1_probability.egg-info/top_level.txt